WGS/SRID300002KOZ.py
WGS/__init__.py
SRID300002KOZ-0.1.0.dist-info/METADATA
SRID300002KOZ-0.1.0.dist-info/WHEEL
SRID300002KOZ-0.1.0.dist-info/top_level.txt
SRID300002KOZ-0.1.0.dist-info/RECORD
